automeans/__init__.py
automeans/cluster.py
automeans-1.0.0.dist-info/LICENSE.txt
automeans-1.0.0.dist-info/METADATA
automeans-1.0.0.dist-info/WHEEL
automeans-1.0.0.dist-info/top_level.txt
automeans-1.0.0.dist-info/RECORD
