Metadata-Version: 2.1
Name: automeans
Version: 1.0.0
Summary: A Python package that helps automate the number of cluster for k-means
Home-page: https://github.com/anshulp2912/automeans
Author: Anshul Patel
Author-email: anshulp2912@gmail.com
License: MIT
Platform: UNKNOWN
Classifier: Programming Language :: Python :: 3.6
Classifier: Programming Language :: Python :: 3.7
Classifier: Programming Language :: Python :: 3.8
Classifier: License :: OSI Approved :: MIT License
Classifier: Operating System :: OS Independent
Requires-Dist: numpy
Requires-Dist: scikit-learn
Requires-Dist: pandas
Requires-Dist: kneed (>=0.7.0)
Requires-Dist: matplotlib (>=3.3.2)
